acdh_arche_pyutils/__init__.py
acdh_arche_pyutils/client.py
acdh_arche_pyutils/utils.py
acdh_arche_pyutils/files/test.txt
acdh_arche_pyutils-0.7.1.dist-info/AUTHORS.rst
acdh_arche_pyutils-0.7.1.dist-info/LICENSE
acdh_arche_pyutils-0.7.1.dist-info/METADATA
acdh_arche_pyutils-0.7.1.dist-info/WHEEL
acdh_arche_pyutils-0.7.1.dist-info/entry_points.txt
acdh_arche_pyutils-0.7.1.dist-info/top_level.txt
acdh_arche_pyutils-0.7.1.dist-info/RECORD
