Metadata-Version: 2.1
Name: acdh-arche-pyutils
Version: 0.7.1
Summary: a python client for ARCHE-API
Home-page: https://github.com/acdh-oeaw/acdh-arche-pyutils
Author: Peter Andorfer
Author-email: peter.andorfer@oeaw.ac.at
License: MIT
Keywords: acdh-arche-pyutils
Platform: UNKNOWN
Classifier: Development Status :: 2 - Pre-Alpha
Classifier: Intended Audience :: Developers
Classifier: License :: OSI Approved :: MIT License
Classifier: Natural Language :: English
Classifier: Programming Language :: Python :: 3
Classifier: Programming Language :: Python :: 3.7
Classifier: Programming Language :: Python :: 3.8
Requires-Python: >=3.7
Requires-Dist: rdflib
Requires-Dist: requests
Requires-Dist: PyYAML
Requires-Dist: sparqlwrapper
Requires-Dist: tqdm
